odd_even/checker.py
odd_even/init.py
mr_odd_even-0.0.1.dist-info/METADATA
mr_odd_even-0.0.1.dist-info/WHEEL
mr_odd_even-0.0.1.dist-info/top_level.txt
mr_odd_even-0.0.1.dist-info/RECORD
