Metadata-Version: 2.4
Name: mr-odd-even
Version: 0.0.1
Summary: A simple odd or even number checker.
Author-email: Your Name <your.email@example.com>
License: MIT
Requires-Python: >=3.7
